eda_mds/__init__.py
eda_mds/cat_var_stats.py
eda_mds/cor_eda.py
eda_mds/describe_outliers.py
eda_mds/info_na.py
eda_mds-2.1.8.dist-info/LICENSE
eda_mds-2.1.8.dist-info/METADATA
eda_mds-2.1.8.dist-info/WHEEL
eda_mds-2.1.8.dist-info/RECORD
