Metadata-Version: 2.1
Name: eda_mds
Version: 2.1.8
Summary: EBasic EDA functions implemented
License: MIT
Author: Koray Tecimer, Paolo De Lagrave-Codina, Nicole Bidwell, Simon Frew
Requires-Python: >=3.9,<4.0
Classifier: License :: OSI Approved :: MIT License
Classifier: Programming Language :: Python :: 3
Classifier: Programming Language :: Python :: 3.9
Classifier: Programming Language :: Python :: 3.10
Classifier: Programming Language :: Python :: 3.11
Classifier: Programming Language :: Python :: 3.12
Requires-Dist: numpy (>=1.26.3,<2.0.0)
Requires-Dist: pandas (>=2.1.4,<3.0.0)
Requires-Dist: python-semantic-release (>=8.7.0,<9.0.0)
